fishhoof/__init__.py
fishhoof/__main__.py
fishhoof/cli.py
fishhoof/find_files.py
fishhoof-0.0.3.dist-info/METADATA
fishhoof-0.0.3.dist-info/WHEEL
fishhoof-0.0.3.dist-info/entry_points.txt
fishhoof-0.0.3.dist-info/RECORD
