Metadata-Version: 2.3
Name: fishhoof
Version: 0.0.3
Summary: Add your description here
Author-email: Taylor Monacelli <taylormonacelli@gmail.com>
Requires-Python: >=3.8
Requires-Dist: humanize>=4.9.0
Requires-Dist: jinja2>=3.1.3
Requires-Dist: pytimeparse>=1.1.8
